datanashor/__init__.py
datanashor/client.py
datanashor/metadata.py
datanashor/parser.py
datanashor/utils/__init__.py
datanashor/utils/calc_gold.py
datanashor/utils/item_patch_parser.py
datanashor/utils/send_serial.py
datanashor-0.4.5.dist-info/LICENSE
datanashor-0.4.5.dist-info/METADATA
datanashor-0.4.5.dist-info/WHEEL
datanashor-0.4.5.dist-info/top_level.txt
datanashor-0.4.5.dist-info/RECORD
