Metadata-Version: 2.1
Name: datanashor
Version: 0.4.5
Summary: League of Legends live replay parser
Home-page: https://github.com/fifteen-GG/DataNashor-Parser
Author: James Jung
Author-email: therealjamesjung@gmail.com
License: MIT
Classifier: Intended Audience :: Developers
Classifier: Programming Language :: Python :: 3
Classifier: License :: OSI Approved :: MIT License
Classifier: Operating System :: Microsoft :: Windows
Requires-Python: >=3.9
License-File: LICENSE
Requires-Dist: requests
Requires-Dist: beautifulsoup4
Requires-Dist: pyserial
